carcore.py
carcore-0.1.1.dist-info/METADATA
carcore-0.1.1.dist-info/WHEEL
carcore-0.1.1.dist-info/RECORD
